{
  "scan_date": "2025-11-11 17:49:24",
  "devices_found": 3,
  "devices": [
    {
      "ip": "192.168.2.1",
      "type": "Grandstream ATA",
      "endpoints": [
        "/index.html"
      ],
      "headers": {
        "Content-Type": "text/html",
        "Accept-Ranges": "bytes",
        "ETag": "\"-1121803611\"",
        "Last-Modified": "Tue, 12 Feb 2019 16:55:08 GMT",
        "Content-Length": "1894",
        "Date": "Wed, 27 Apr 2022 17:28:41 GMT",
        "Server": "lighttpd/1.4.35"
      },
      "credentials": [
        "admin",
        "admin"
      ]
    },
    {
      "ip": "192.168.100.1",
      "type": "ONT (Fiberhome/similar)",
      "endpoints": [
        "/index.html"
      ],
      "headers": {
        "Date": "Tue, 11 Nov 2025 17:49:13 GMT",
        "Content-Type": "text/html; charset=utf-8",
        "Content-Length": "2519",
        "Connection": "keep-alive",
        "Expires": "Tue, 11 Nov 2025 17:49:12 GMT",
        "Cache-Control": "no-cache, no-cache, no-store, max-age=0, must-revalidate",
        "X-Frame-Options": "SAMEORIGIN",
        "X-Content-Type-Options": "nosniff",
        "X-XSS-Protection": "1; mode=block",
        "pragma": "no-cache",
        "X-Download-Options": "noopen",
        "X-Permitted-Cross-Domain-Policies": "master-only",
        "Referrer-Policy": "no-referrer-when-downgrade",
        "Accept-Ranges": "bytes"
      },
      "credentials": [
        "admin",
        "admin"
      ]
    },
    {
      "ip": "192.168.100.1",
      "type": "ONT (Fiberhome/similar)",
      "endpoints": [
        "/index.html"
      ],
      "headers": {
        "Date": "Tue, 11 Nov 2025 17:49:13 GMT",
        "Content-Type": "text/html; charset=utf-8",
        "Content-Length": "2519",
        "Connection": "keep-alive",
        "Expires": "Tue, 11 Nov 2025 17:49:12 GMT",
        "Cache-Control": "no-cache, no-cache, no-store, max-age=0, must-revalidate",
        "X-Frame-Options": "SAMEORIGIN",
        "X-Content-Type-Options": "nosniff",
        "X-XSS-Protection": "1; mode=block",
        "pragma": "no-cache",
        "X-Download-Options": "noopen",
        "X-Permitted-Cross-Domain-Policies": "master-only",
        "Referrer-Policy": "no-referrer-when-downgrade",
        "Accept-Ranges": "bytes"
      },
      "credentials": [
        "admin",
        "admin"
      ]
    }
  ]
}